src/immediate_gen.sv
/*
@Author: Tawhid Alam
@Date: 2024-06-01 12:00:00
@Last Modified by: Tawhid Alam
@Last Modified time: 2024-06-01 12:00:00

== Description ==
-parameterized immediate generator for RISC-V instructions
-Generates the correct immediate value based on the instruction type (I, S, B, U, J)
-Supports sign-extension for negative immediates

== Inputs ==
-instr: 32-bit instruction from which the immediate value will be extracted
== Outputs ==
-imm_out: 32-bit immediate value generated based on the instruction type

== Local Parameters ==
    I_TYPE = 7'b0010011,
    LOAD   = 7'b0000011,
    STORE  = 7'b0100011,
    BRANCH = 7'b1100011,
    JAL    = 7'b1101111,
    JALR   = 7'b1100111,
    LUI    = 7'b0110111,
    AUIPC  = 7'b0010111;

== Instruction Types immediate values ==
    I-type: instr[31:20]
    S-type: instr[31:25] & instr[11:7]
    B-type: instr[7] & instr[30:25] & instr[11:8] & 1'b0
    U-type: instr[31:12] & 12'b0
    J-type: instr[19:12] & instr[20] & instr[30:21] & 1'b0
*/

module immediate_gen (
    input  logic [31:0] instr,
    output logic [31:0] imm_out
);

    logic [6:0] opcode;
    assign opcode = instr[6:0];

    localparam I_TYPE = 7'b0010011,   // ADDI, SLTI, XORI, ORI, ANDI, SLLI, SRLI, SRAI
               LOAD   = 7'b0000011,   // LB, LH, LW, LBU, LHU
               STORE  = 7'b0100011,   // SB, SH, SW
               BRANCH = 7'b1100011,   // BEQ, BNE, BLT, BGE, BLTU, BGEU
               JAL    = 7'b1101111,
               JALR   = 7'b1100111,
               LUI    = 7'b0110111,
               AUIPC  = 7'b0010111;

    always_comb begin
        case (opcode)
            // I-type: 12-bit signed immediate
            I_TYPE,
            LOAD,
            JALR   : imm_out = {{20{instr[31]}}, instr[31:20]};

            // S-type: split across two fields
            STORE  : imm_out = {{20{instr[31]}}, instr[31:25], instr[11:7]};

            // B-type: branch offset (bit-1 to bit-12, bit-0 always 0)
            BRANCH : imm_out = {{20{instr[31]}}, instr[7], instr[30:25], instr[11:8], 1'b0};

            // U-type: upper 20 bits, lower 12 zeroed
            LUI,
            AUIPC  : imm_out = {instr[31:12], 12'b0};

            // J-type: jump offset (bit-1 to bit-20, bit-0 always 0)
            JAL    : imm_out = {{12{instr[31]}}, instr[19:12], instr[20], instr[30:21], 1'b0};

            default: imm_out = 32'b0;
        endcase
    end

endmodule

tb/imm_gen_tb.sv
// =============================================================
// TESTBENCH : immediate_gen
// PURPOSE   : Verify all 5 immediate formats.
//             The J-type backward test is the critical one —
//             it catches the {11{...}} vs {12{...}} bug.
// =============================================================

module imm_gen_tb;

    logic [31:0] instr;
    logic [31:0] imm_out;

    // DUT
    immediate_gen dut (
        .instr(instr), 
        .imm_out(imm_out)
    );

    // -------------------------------------------------------
    // Scoreboard
    // -------------------------------------------------------
    int pass_count = 0;
    int fail_count = 0;

    task automatic check(input string name, input logic [31:0] expected);
        #1;
        if (imm_out === expected) begin
            $display("  PASS | %-30s | 0x%08X", name, imm_out);
            pass_count++;
        end else begin
            $display("  FAIL | %-30s | got 0x%08X  expected 0x%08X",
                     name, imm_out, expected);
            fail_count++;
        end
    endtask

    initial begin
        $dumpfile("imm_gen_waves.vcd");          // filename — put wherever you want
        $dumpvars(0, imm_gen_tb);        // 0 = dump ALL signals, all hierarchy levels
        
        $display("\n====== IMMEDIATE GENERATOR TEST ======");

        // --- I-TYPE ---
        // ADDI x1, x0, 5   → imm = 5
        instr = 32'h00500093;
        check("I-type  +5", 32'd5);

        // ADDI x1, x0, -1  → imm = 0xFFFFFFFF
        // Also tests decoder bug: instr[30]=1 here is PART OF IMM
        instr = 32'hFFF00093;
        check("I-type  -1", 32'hFFFFFFFF);

        // --- S-TYPE ---
        // SW x2, 8(x1)  → imm = 8
        instr = 32'h0020A423;
        check("S-type  +8", 32'd8);

        // --- B-TYPE ---
        // BEQ x0, x0, +8  → imm = 8
        instr = 32'h00000463;
        check("B-type  +8", 32'd8);

        // BEQ x0, x0, -8  → imm = 0xFFFFFFF8
        instr = 32'hFE000CE3;
        check("B-type  -8", 32'hFFFFFFF8);

        // --- U-TYPE ---
        // LUI x1, 0x12345  → imm = 0x12345000
        instr = 32'h123450B7;
        check("U-type  0x12345000", 32'h12345000);

        // --- J-TYPE ---
        // JAL x0, +8  → imm = 8
        instr = 32'h0080006F;
        check("J-type  +8 (forward)", 32'd8);

        // JAL x0, -8  → imm = 0xFFFFFFF8
        // *** THIS IS THE BUG-FIX TEST ***
        // Old code ({11{...}}) gives 0x7FFFFFF8 here (WRONG)
        // Fixed code ({12{...}}) gives 0xFFFFFFF8 (CORRECT)
        instr = 32'hFF9FF06F;
        check("J-type  -8 (backward) <-- BUG FIX", 32'hFFFFFFF8);

        // --- SUMMARY ---
        $display("\n  %0d passed,  %0d failed", pass_count, fail_count);
        if (fail_count == 0) $display("  ALL PASSED\n");
        else                 $display("  FAILURES ABOVE ^^^\n");

        $finish;
    end

endmodule

sim_result/waves/imm_gen_waves.vcd
$version Generated by VerilatedVcd $end
$timescale 1ps $end
 $scope module TOP $end
  $scope module imm_gen_tb $end
   $var wire 32 # instr [31:0] $end
   $var wire 32 $ imm_out [31:0] $end
   $var wire 32 % pass_count [31:0] $end
   $var wire 32 & fail_count [31:0] $end
   $scope module dut $end
    $var wire 32 # instr [31:0] $end
    $var wire 32 $ imm_out [31:0] $end
    $var wire 7 ' opcode [6:0] $end
    $var wire 7 ( I_TYPE [6:0] $end
    $var wire 7 ) LOAD [6:0] $end
    $var wire 7 * STORE [6:0] $end
    $var wire 7 + BRANCH [6:0] $end
    $var wire 7 , JAL [6:0] $end
    $var wire 7 - JALR [6:0] $end
    $var wire 7 . LUI [6:0] $end
    $var wire 7 / AUIPC [6:0] $end
   $upscope $end
  $upscope $end
 $upscope $end
$enddefinitions $end


#0
b00000000010100000000000010010011 #
b00000000000000000000000000000101 $
b00000000000000000000000000000000 %
b00000000000000000000000000000000 &
b0010011 '
b0010011 (
b0000011 )
b0100011 *
b1100011 +
b1101111 ,
b1100111 -
b0110111 .
b0010111 /
#1
b11111111111100000000000010010011 #
b11111111111111111111111111111111 $
b00000000000000000000000000000001 %
#2
b00000000001000001010010000100011 #
b00000000000000000000000000001000 $
b00000000000000000000000000000010 %
b0100011 '
#3
b00000000000000000000010001100011 #
b00000000000000000000000000000011 %
b1100011 '
#4
b11111110000000000000110011100011 #
b11111111111111111111111111111000 $
b00000000000000000000000000000100 %
#5
b00010010001101000101000010110111 #
b00010010001101000101000000000000 $
b00000000000000000000000000000101 %
b0110111 '
#6
b00000000100000000000000001101111 #
b00000000000000000000000000001000 $
b00000000000000000000000000000110 %
b1101111 '
#7
b11111111100111111111000001101111 #
b11111111111111111111111111111000 $
b00000000000000000000000000000111 %
#8
b00000000000000000000000000001000 %
