src/decoder.sv
/*


31        25 24    20 19    15 14  12 11     7 6        0
 ┌──────────┬────────┬────────┬──────┬────────┬─────────┐
 │  funct7  │  rs2   │  rs1   │funct3│   rd   │ opcode  │
 │  [31:25] │[24:20] │[19:15] │[14:12│[11: 7] │ [6:0]   │
 └──────────┴────────┴────────┴──────┴────────┴─────────┘
    7bits     5bits    5bits    3bits   5bits    7bits

- The opcode field (bits [6:0]) is used to determine the instruction type and the specific operation to be performed.
- The funct3 field (bits [14:12]) and funct7 field
- (bits [31:25]) are used in conjunction with the opcode to further specify the exact operation, especially for R-type instructions.
- The rs1 and rs2 fields (bits [19:15] and [24:20]) specify the source registers, while the rd field (bits [11:7]) specifies the destination register for the result of the operation.
- The testbench for this module should verify that the decoder correctly identifies the opcode and sets the


*/

module decoder (
    input  logic [31:0] instr,

    // ALU control
    output logic [3:0]  alu_op,
    output logic [1:0]  alu_a_src,   // 00=rs1  01=PC  10=zero
    output logic        alu_src,     // 0=rs2   1=imm  (ALU B input)

    // Register file
    output logic        reg_write,

    // Data memory
    output logic        mem_write,   // 1 = store
    output logic        mem_read,    // 1 = load
    output logic [2:0]  mem_size,    // funct3: encodes width + sign for load/store

    // Writeback
    output logic [1:0]  wb_sel,      // 00=ALU  01=memory  10=PC+4

    // Branch / Jump
    output logic        branch,
    output logic [2:0]  branch_op,   // funct3 of branch → tells top module which condition
    output logic        jump,
    output logic        jalr         // 1=JALR, 0=JAL  (valid only when jump=1)
);

    // -------------------------------------------------------------------------
    // Instruction field extraction
    // -------------------------------------------------------------------------
    logic [6:0] opcode;
    logic [2:0] funct3;
    logic [6:0] funct7;

    assign opcode = instr[6:0];
    assign funct3 = instr[14:12];
    assign funct7 = instr[31:25];

    // -------------------------------------------------------------------------
    // Opcode parameters
    // -------------------------------------------------------------------------
    localparam R_TYPE = 7'b0110011,
               I_TYPE = 7'b0010011,
               LOAD   = 7'b0000011,
               STORE  = 7'b0100011,
               BRANCH = 7'b1100011,
               JAL    = 7'b1101111,
               JALR   = 7'b1100111,
               LUI    = 7'b0110111,
               AUIPC  = 7'b0010111;

    // ALU A source encoding
    localparam ALU_A_RS1  = 2'b00,   // default
               ALU_A_PC   = 2'b01,   // AUIPC
               ALU_A_ZERO = 2'b10;   // LUI

    // Writeback select encoding
    localparam WB_ALU = 2'b00,
               WB_MEM = 2'b01,
               WB_PC4 = 2'b10;

    // -------------------------------------------------------------------------
    // Decode logic
    // -------------------------------------------------------------------------
    always_comb begin

        // Safe defaults — NOP behaviour
        alu_op    = 4'b0000;
        alu_a_src = ALU_A_RS1;
        alu_src   = 1'b0;
        reg_write = 1'b0;
        mem_write = 1'b0;
        mem_read  = 1'b0;
        mem_size  = 3'b010;          // word (SW/LW) as harmless default
        wb_sel    = WB_ALU;
        branch    = 1'b0;
        branch_op = 3'b000;
        jump      = 1'b0;
        jalr      = 1'b0;

        case (opcode)

            // -----------------------------------------------------------------
            // R-TYPE: ADD, SUB, SLL, SLT, SLTU, XOR, SRL, SRA, OR, AND
            // alu_op = {funct7[5], funct3} — safe here, funct7 is a real field
            // -----------------------------------------------------------------
            R_TYPE: begin
                reg_write = 1'b1;
                alu_op    = {funct7[5], funct3};
                wb_sel    = WB_ALU;
            end

            // -----------------------------------------------------------------
            // I-TYPE: ADDI, SLTI, SLTIU, XORI, ORI, ANDI, SLLI, SRLI, SRAI
            //
            // BUG FIX: instr[30] is part of the immediate for most I-type ops.
            // Only SRLI vs SRAI (funct3 == 101) legitimately uses instr[30].
            // For all others, force the MSB of alu_op to 0.
            // -----------------------------------------------------------------
            I_TYPE: begin
                reg_write = 1'b1;
                alu_src   = 1'b1;    // ALU B = immediate
                wb_sel    = WB_ALU;
                // Use instr[30] only for shift-right to distinguish SRLI/SRAI
                alu_op    = (funct3 == 3'b101) ? {funct7[5], funct3}  // SRLI or SRAI
                                               : {1'b0,      funct3}; // all others: ignore bit[30]
            end

            // -----------------------------------------------------------------
            // LOAD: LB, LH, LW, LBU, LHU
            // funct3 encodes both width and signed/unsigned for data_mem
            // -----------------------------------------------------------------
            LOAD: begin
                reg_write = 1'b1;
                alu_src   = 1'b1;       // addr = rs1 + sign_ext(imm)
                mem_read  = 1'b1;
                mem_size  = funct3;     // passed to data_mem for read decoding
                alu_op    = 4'b0000;    // ADD for address calculation
                wb_sel    = WB_MEM;
            end

            // -----------------------------------------------------------------
            // STORE: SB, SH, SW
            // -----------------------------------------------------------------
            STORE: begin
                alu_src   = 1'b1;       // addr = rs1 + sign_ext(imm)
                mem_write = 1'b1;
                mem_size  = funct3;     // passed to data_mem for byte-enable generation
                alu_op    = 4'b0000;    // ADD for address calculation
            end

            // -----------------------------------------------------------------
            // BRANCH: BEQ, BNE, BLT, BGE, BLTU, BGEU
            // ALU computes comparison; top module evaluates the condition flag
            // branch_op (= funct3) tells the top module which flag to check
            // -----------------------------------------------------------------
            BRANCH: begin
                branch    = 1'b1;
                branch_op = funct3;
                // Select ALU op to produce the right comparison result
                case (funct3)
                    3'b000,
                    3'b001: alu_op = 4'b1000;  // BEQ / BNE  → SUB  → check zero flag
                    3'b100,
                    3'b101: alu_op = 4'b0010;  // BLT / BGE  → SLT  → check result[0]
                    3'b110,
                    3'b111: alu_op = 4'b0011;  // BLTU / BGEU → SLTU → check result[0]
                    default: alu_op = 4'b1000;
                endcase
            end

            // -----------------------------------------------------------------
            // JAL: rd = PC+4,  PC = PC + sign_ext(imm)
            // ALU is not used for target — target computed in top module
            // -----------------------------------------------------------------
            JAL: begin
                reg_write = 1'b1;
                jump      = 1'b1;
                jalr      = 1'b0;
                wb_sel    = WB_PC4;     // write return address to rd
            end

            // -----------------------------------------------------------------
            // JALR: rd = PC+4,  PC = (rs1 + sign_ext(imm)) & ~1
            // ALU computes the target; top module clears LSB
            // -----------------------------------------------------------------
            JALR: begin
                reg_write = 1'b1;
                alu_src   = 1'b1;       // ALU B = immediate
                alu_op    = 4'b0000;    // ADD: rs1 + imm = raw jump target
                jump      = 1'b1;
                jalr      = 1'b1;
                wb_sel    = WB_PC4;     // write return address to rd
            end

            // -----------------------------------------------------------------
            // LUI: rd = 0 + imm  (upper 20 bits, lower 12 zeroed by imm_gen)
            // Force ALU A input to 0 so result = 0 + imm = imm
            // -----------------------------------------------------------------
            LUI: begin
                reg_write = 1'b1;
                alu_src   = 1'b1;
                alu_a_src = ALU_A_ZERO; // A = 0
                alu_op    = 4'b0000;    // ADD: 0 + imm = imm
                wb_sel    = WB_ALU;
            end

            // -----------------------------------------------------------------
            // AUIPC: rd = PC + imm
            // Force ALU A input to PC
            // -----------------------------------------------------------------
            AUIPC: begin
                reg_write = 1'b1;
                alu_src   = 1'b1;
                alu_a_src = ALU_A_PC;   // A = PC
                alu_op    = 4'b0000;    // ADD: PC + imm
                wb_sel    = WB_ALU;
            end

            // -----------------------------------------------------------------
            // Unknown opcode — all signals stay at safe NOP defaults
            // -----------------------------------------------------------------
            default: ;

        endcase
    end

endmodule

tb/decoder_tb.sv
// =============================================================
// TESTBENCH : decoder
// PURPOSE   : Verify every control signal for every opcode.
//             Special attention to:
//             - I-type alu_op bug fix (ADDI with neg imm)
//             - New signals: alu_a_src, wb_sel, jalr, branch_op
// =============================================================

//systemverilog =============================================================
// TESTBENCH : decoder
// PURPOSE   : Verify every control signal for every opcode.
// =============================================================

module decoder_tb;

    logic [31:0] instr;

    logic [3:0]  alu_op;
    logic [1:0]  alu_a_src;
    logic        alu_src;
    logic        reg_write;
    logic        mem_write;
    logic        mem_read;
    logic [2:0]  mem_size;
    logic [1:0]  wb_sel;
    logic        branch;
    logic [2:0]  branch_op;
    logic        jump;
    logic        jalr;

    decoder dut (.*);

    int pass_count = 0;
    int fail_count = 0;

    // -------------------------------------------------------
    // chk1 : for 1-bit signals
    // -------------------------------------------------------
    task automatic chk1(input string name,
                        input logic   got,
                        input logic   exp);
        if (got === exp) begin
            $display("      OK   %-12s = %0b", name, got);
            pass_count++;
        end else begin
            $display("      FAIL %-12s = %0b  (expected %0b)", name, got, exp);
            fail_count++;
        end
    endtask

    // -------------------------------------------------------
    // chk4 : for multi-bit signals (2, 3, or 4 bits)
    // -------------------------------------------------------
    task automatic chk4(input string      name,
                        input logic [3:0] got,
                        input logic [3:0] exp);
        if (got === exp) begin
            $display("      OK   %-12s = %04b", name, got);
            pass_count++;
        end else begin
            $display("      FAIL %-12s = %04b  (expected %04b)", name, got, exp);
            fail_count++;
        end
    endtask

    initial begin
        $dumpfile("waves_decoder.vcd");
        $dumpvars(0, decoder_tb);

        $display("\n====== DECODER TEST ======");

        // ---------------------------------------------------
        // 1. R-TYPE : ADD x3, x1, x2   → 0x002080B3
        // ---------------------------------------------------
        $display("\n[1] R-TYPE  ADD x3, x1, x2");
        instr = 32'h002080B3; #1;
        chk4("alu_op",    alu_op,    4'b0000);  // ADD
        chk1("alu_src",   alu_src,   1'b0);     // rs2
        chk1("reg_write", reg_write, 1'b1);
        chk1("mem_write", mem_write, 1'b0);
        chk1("mem_read",  mem_read,  1'b0);
        chk4("wb_sel",    wb_sel,    2'b00);    // ALU result

        // ---------------------------------------------------
        // 2. I-TYPE POSITIVE : ADDI x1, x0, +5   → 0x00500093
        // ---------------------------------------------------
        $display("\n[2] I-TYPE  ADDI x1, x0, +5");
        instr = 32'h00500093; #1;
        chk4("alu_op",    alu_op,    4'b0000);  // ADD
        chk1("alu_src",   alu_src,   1'b1);     // immediate
        chk1("reg_write", reg_write, 1'b1);
        chk4("wb_sel",    wb_sel,    2'b00);

        // ---------------------------------------------------
        // 3. I-TYPE NEGATIVE : ADDI x1, x0, -1   → 0xFFF00093
        //    instr[30]=1 here — part of the immediate, NOT funct7.
        //    BUG FIX: alu_op must be ADD (0000), not SUB (1000).
        // ---------------------------------------------------
        $display("\n[3] I-TYPE  ADDI x1, x0, -1  (bug-fix: must be ADD not SUB)");
        instr = 32'hFFF00093; #1;
        chk4("alu_op",    alu_op,    4'b0000);  // ADD — would be 1000 without fix
        chk1("alu_src",   alu_src,   1'b1);
        chk1("reg_write", reg_write, 1'b1);

        // ---------------------------------------------------
        // 4. LOAD : LW x5, 0(x1)   → 0x0000A283
        // ---------------------------------------------------
        $display("\n[4] LOAD  LW x5, 0(x1)");
        instr = 32'h0000A283; #1;
        chk4("alu_op",    alu_op,    4'b0000);  // ADD (address calc)
        chk1("alu_src",   alu_src,   1'b1);
        chk1("mem_read",  mem_read,  1'b1);
        chk1("mem_write", mem_write, 1'b0);
        chk1("reg_write", reg_write, 1'b1);
        chk4("wb_sel",    wb_sel,    2'b01);    // memory data

        // ---------------------------------------------------
        // 5. STORE : SW x2, 0(x1)   → 0x0020A023
        // ---------------------------------------------------
        $display("\n[5] STORE  SW x2, 0(x1)");
        instr = 32'h0020A023; #1;
        chk4("alu_op",    alu_op,    4'b0000);
        chk1("alu_src",   alu_src,   1'b1);
        chk1("mem_write", mem_write, 1'b1);
        chk1("mem_read",  mem_read,  1'b0);
        chk1("reg_write", reg_write, 1'b0);    // no writeback

        // ---------------------------------------------------
        // 6. BRANCH : BNE x10, x0, +8   → 0x00051463
        // ---------------------------------------------------
        $display("\n[6] BRANCH  BNE x10, x0, +8");
        instr = 32'h00051463; #1;
        chk1("branch",    branch,    1'b1);
        chk4("branch_op", branch_op, 3'b001);  // BNE = funct3 001
        chk4("alu_op",    alu_op,    4'b1000);  // SUB (zero flag check)
        chk1("reg_write", reg_write, 1'b0);
        chk1("jump",      jump,      1'b0);
        chk1("mem_write", mem_write, 1'b0);

        // ---------------------------------------------------
        // 7. JAL : JAL x1, 0   → 0x000000EF
        // ---------------------------------------------------
        $display("\n[7] JAL  x1, 0");
        instr = 32'h000000EF; #1;
        chk1("jump",      jump,      1'b1);
        chk1("jalr",      jalr,      1'b0);    // JAL not JALR
        chk1("reg_write", reg_write, 1'b1);
        chk4("wb_sel",    wb_sel,    2'b10);   // PC+4 (return address)
        chk1("branch",    branch,    1'b0);

        // ---------------------------------------------------
        // 8. JALR : JALR x1, 0(x2)   → 0x000100E7
        // ---------------------------------------------------
        $display("\n[8] JALR  x1, 0(x2)");
        instr = 32'h000100E7; #1;
        chk1("jump",      jump,      1'b1);
        chk1("jalr",      jalr,      1'b1);    // is JALR
        chk1("alu_src",   alu_src,   1'b1);    // rs1 + imm for target
        chk1("reg_write", reg_write, 1'b1);
        chk4("wb_sel",    wb_sel,    2'b10);   // PC+4 (return address)

        // ---------------------------------------------------
        // 9. LUI : LUI x5, 0x12345   → 0x123452B7
        // ---------------------------------------------------
        $display("\n[9] LUI  x5, 0x12345");
        instr = 32'h123452B7; #1;
        chk4("alu_a_src", alu_a_src, 2'b10);  // A = 0 (so rd = 0 + imm)
        chk1("alu_src",   alu_src,   1'b1);
        chk1("reg_write", reg_write, 1'b1);
        chk4("wb_sel",    wb_sel,    2'b00);   // ALU result
        chk1("mem_write", mem_write, 1'b0);

        // ---------------------------------------------------
        // 10. AUIPC : AUIPC x5, 0x12345   → 0x12345297
        // ---------------------------------------------------
        $display("\n[10] AUIPC  x5, 0x12345");
        instr = 32'h12345297; #1;
        chk4("alu_a_src", alu_a_src, 2'b01);  // A = PC (so rd = PC + imm)
        chk1("alu_src",   alu_src,   1'b1);
        chk1("reg_write", reg_write, 1'b1);
        chk4("wb_sel",    wb_sel,    2'b00);

        // ---------------------------------------------------
        // Summary
        // ---------------------------------------------------
        $display("\n  %0d passed,  %0d failed", pass_count, fail_count);
        if (fail_count == 0) $display("  ALL PASSED\n");
        else                 $display("  FAILURES ABOVE ^^^\n");

        $finish;
    end

endmodule

sim_result/waves/waves_decoder.vcd
$version Generated by VerilatedVcd $end
$timescale 1ps $end
 $scope module TOP $end
  $scope module decoder_tb $end
   $var wire 32 # instr [31:0] $end
   $var wire 4 ) alu_op [3:0] $end
   $var wire 2 * alu_a_src [1:0] $end
   $var wire 1 + alu_src $end
   $var wire 1 , reg_write $end
   $var wire 1 - mem_write $end
   $var wire 1 . mem_read $end
   $var wire 3 / mem_size [2:0] $end
   $var wire 2 0 wb_sel [1:0] $end
   $var wire 1 1 branch $end
   $var wire 3 2 branch_op [2:0] $end
   $var wire 1 3 jump $end
   $var wire 1 4 jalr $end
   $var wire 32 $ pass_count [31:0] $end
   $var wire 32 % fail_count [31:0] $end
   $scope module dut $end
    $var wire 32 # instr [31:0] $end
    $var wire 4 ) alu_op [3:0] $end
    $var wire 2 * alu_a_src [1:0] $end
    $var wire 1 + alu_src $end
    $var wire 1 , reg_write $end
    $var wire 1 - mem_write $end
    $var wire 1 . mem_read $end
    $var wire 3 / mem_size [2:0] $end
    $var wire 2 0 wb_sel [1:0] $end
    $var wire 1 1 branch $end
    $var wire 3 2 branch_op [2:0] $end
    $var wire 1 3 jump $end
    $var wire 1 4 jalr $end
    $var wire 7 & opcode [6:0] $end
    $var wire 3 ' funct3 [2:0] $end
    $var wire 7 ( funct7 [6:0] $end
    $var wire 7 5 R_TYPE [6:0] $end
    $var wire 7 6 I_TYPE [6:0] $end
    $var wire 7 7 LOAD [6:0] $end
    $var wire 7 8 STORE [6:0] $end
    $var wire 7 9 BRANCH [6:0] $end
    $var wire 7 : JAL [6:0] $end
    $var wire 7 ; JALR [6:0] $end
    $var wire 7 < LUI [6:0] $end
    $var wire 7 = AUIPC [6:0] $end
    $var wire 2 > ALU_A_RS1 [1:0] $end
    $var wire 2 ? ALU_A_PC [1:0] $end
    $var wire 2 @ ALU_A_ZERO [1:0] $end
    $var wire 2 > WB_ALU [1:0] $end
    $var wire 2 ? WB_MEM [1:0] $end
    $var wire 2 @ WB_PC4 [1:0] $end
   $upscope $end
  $upscope $end
 $upscope $end
$enddefinitions $end


#0
b00000000001000001000000010110011 #
b00000000000000000000000000000000 $
b00000000000000000000000000000000 %
b0110011 &
b000 '
b0000000 (
b0000 )
b00 *
0+
1,
0-
0.
b010 /
b00 0
01
b000 2
03
04
b0110011 5
b0010011 6
b0000011 7
b0100011 8
b1100011 9
b1101111 :
b1100111 ;
b0110111 <
b0010111 =
b00 >
b01 ?
b10 @
#1
b00000000010100000000000010010011 #
b00000000000000000000000000000110 $
b0010011 &
1+
#2
b11111111111100000000000010010011 #
b00000000000000000000000000001010 $
b1111111 (
#3
b00000000000000001010001010000011 #
b00000000000000000000000000001101 $
b0000011 &
b010 '
b0000000 (
1.
b01 0
#4
b00000000001000001010000000100011 #
b00000000000000000000000000010011 $
b0100011 &
0,
1-
0.
b00 0
#5
b00000000000001010001010001100011 #
b00000000000000000000000000011000 $
b1100011 &
b001 '
b1000 )
0+
0-
11
b001 2
#6
b00000000000000000000000011101111 #
b00000000000000000000000000011110 $
b1101111 &
b000 '
b0000 )
1,
b10 0
01
b000 2
13
#7
b00000000000000010000000011100111 #
b00000000000000000000000000100011 $
b1100111 &
1+
14
#8
b00010010001101000101001010110111 #
b00000000000000000000000000101000 $
b0110111 &
b101 '
b0001001 (
b10 *
b00 0
03
04
#9
b00010010001101000101001010010111 #
b00000000000000000000000000101101 $
b0010111 &
b01 *
#10
b00000000000000000000000000110001 $
