src/data_mem.sv
/*
@file data_mem.sv
Data Memory Module for RISC-V Processor
@author [Tawhid Alam]
@date 2024-05-10
@description
- Implements a 4 KB data memory (1024 words × 32 bits)
- Supports byte, halfword, and word accesses with proper sign/zero extension for loads
- Supports byte-lane selective writes for stores
- Synchronous write operations on the rising edge of the clock
- Asynchronous read operations with combinational logic for load data generation
- The testbench for this module should verify that the data memory correctly handles various load and store operations, including edge cases such as unaligned accesses and boundary conditions. It should also include waveform dumping for visualization in GTKWave and display the output data for verification.
- The testbench should cover multiple scenarios, such as storing and loading bytes, halfwords,
and words, as well as verifying that the correct sign or zero extension is applied for load operations. It should also verify that the byte-lane selective writes are functioning correctly by checking the contents of the memory after various store operations.
*/



module data_mem (
    input  logic        clk,
    input  logic        rst,
    input  logic        mem_write,
    input  logic        mem_read,
    input  logic [2:0]  mem_size,
    input  logic [31:0] addr,
    input  logic [31:0] data_in,
    output logic [31:0] data_out
);

    logic [31:0] mem [0:1023];

    logic [9:0] word_addr;
    logic [1:0] byte_offset;

    assign word_addr   = addr[11:2];
    assign byte_offset = addr[1:0];

    // =========================================================================
    // WRITE — synchronous
    // RISC-V rule: store data is ALWAYS in the lower bits of rs2 (data_in).
    //   SB: byte  to write is in data_in[7:0]  — route to selected byte lane
    //   SH: half  to write is in data_in[15:0] — route to selected halfword
    //   SW: word  to write is in data_in[31:0] — write all 4 bytes directly
    // =========================================================================
    always_ff @(posedge clk) begin
        if (rst) begin
            for (int i = 0; i < 1024; i++)
                mem[i] = 32'b0;
        end else if (mem_write) begin
            case (mem_size[1:0])

                // SB — always read from data_in[7:0]
                2'b00: case (byte_offset)
                    2'b00: mem[word_addr][ 7: 0] = data_in[7:0];
                    2'b01: mem[word_addr][15: 8] = data_in[7:0];
                    2'b10: mem[word_addr][23:16] = data_in[7:0];
                    2'b11: mem[word_addr][31:24] = data_in[7:0];
                endcase

                // SH — always read from data_in[15:0]
                2'b01: if (byte_offset[1] == 1'b0)
                    mem[word_addr][15: 0] = data_in[15:0];   // lower halfword
                else
                    mem[word_addr][31:16] = data_in[15:0];   // upper halfword

                // SW — full word
                default: mem[word_addr] = data_in;

            endcase
        end
    end

    // =========================================================================
    // READ — asynchronous (combinational), with sign/zero extension
    // =========================================================================
    logic [31:0] raw_word;
    assign raw_word = mem[word_addr];

    always_comb begin
        data_out = 32'b0;
        if (mem_read) begin
            case (mem_size)
                3'b000: case (byte_offset)          // LB  signed
                    2'b00: data_out = {{24{raw_word[ 7]}}, raw_word[ 7: 0]};
                    2'b01: data_out = {{24{raw_word[15]}}, raw_word[15: 8]};
                    2'b10: data_out = {{24{raw_word[23]}}, raw_word[23:16]};
                    2'b11: data_out = {{24{raw_word[31]}}, raw_word[31:24]};
                endcase
                3'b001: data_out = byte_offset[1]   // LH  signed
                    ? {{16{raw_word[31]}}, raw_word[31:16]}
                    : {{16{raw_word[15]}}, raw_word[15: 0]};
                3'b010: data_out = raw_word;         // LW
                3'b100: case (byte_offset)           // LBU unsigned
                    2'b00: data_out = {24'b0, raw_word[ 7: 0]};
                    2'b01: data_out = {24'b0, raw_word[15: 8]};
                    2'b10: data_out = {24'b0, raw_word[23:16]};
                    2'b11: data_out = {24'b0, raw_word[31:24]};
                endcase
                3'b101: data_out = byte_offset[1]   // LHU unsigned
                    ? {16'b0, raw_word[31:16]}
                    : {16'b0, raw_word[15: 0]};
                default: data_out = raw_word;
            endcase
        end
    end

endmodule

tb/data_mem_tb.sv
// =============================================================
// TESTBENCH : data_mem
// PURPOSE   : Verify byte-enable writes and sign/zero-ext reads.
//             Covers SW/LW, SH/LH/LHU, SB/LB/LBU.
// =============================================================

module data_mem_tb;

    logic        clk, rst;
    logic        mem_write, mem_read;
    logic [2:0]  mem_size;
    logic [31:0] addr, data_in, data_out;

    // DUT
    data_mem dut (.*);

    // 10 MHz clock
    always #5 clk = ~clk;

    int pass_count = 0;
    int fail_count = 0;

    task automatic check(input string name, input logic [31:0] expected);
        if (data_out === expected) begin
            $display("  PASS | %-30s | 0x%08X", name, data_out);
            pass_count++;
        end else begin
            $display("  FAIL | %-30s | got 0x%08X  expected 0x%08X",
                     name, data_out, expected);
            fail_count++;
        end
    endtask

    // Helper: do a 1-cycle write, then read back
    task automatic write_word(input [31:0] a, input [31:0] d, input [2:0] sz);
        @(negedge clk);
        addr      = a;
        data_in   = d;
        mem_write = 1;
        mem_read  = 0;
        mem_size  = sz;
        @(posedge clk); #1;   // write commits on rising edge
        mem_write = 0;
    endtask

    task automatic read_word(input [31:0] a, input [2:0] sz);
        @(negedge clk);
        addr     = a;
        mem_read = 1;
        mem_size = sz;
        #1;                   // combinational — data_out valid immediately
    endtask

    initial begin

        $dumpfile("waves_data_mem.vcd");
        $dumpvars(0, data_mem_tb);

        // Init
        clk = 0; rst = 1; mem_write = 0; mem_read = 0;
        addr = 0; data_in = 0; mem_size = 3'b010;

        repeat(2) @(posedge clk); rst = 0;

        $display("\n====== DATA MEMORY TEST ======");

        // ---------------------------------------------------
        // TEST 1: SW / LW  (full word)
        // Write 0xDEADBEEF to address 0x100, read back
        // ---------------------------------------------------
        $display("\n[1] SW / LW at addr=0x100");
        write_word(32'h100, 32'hDEADBEEF, 3'b010);   // SW
        read_word(32'h100, 3'b010);                    // LW
        check("LW 0xDEADBEEF", 32'hDEADBEEF);

        mem_read = 0;

        // ---------------------------------------------------
        // TEST 2: SH / LH / LHU  (lower halfword)
        // Write 0xABCD to lower halfword of address 0x200.
        // LH  should sign-extend (bit15=1) → 0xFFFFABCD
        // LHU should zero-extend           → 0x0000ABCD
        // ---------------------------------------------------
        $display("\n[2] SH / LH / LHU at addr=0x200");
        write_word(32'h200, 32'h0000ABCD, 3'b001);    // SH (lower)
        read_word(32'h200, 3'b001);
        check("LH  0xFFFFABCD (signed)", 32'hFFFFABCD);
        read_word(32'h200, 3'b101);
        check("LHU 0x0000ABCD (unsigned)", 32'h0000ABCD);

        mem_read = 0;

        // ---------------------------------------------------
        // TEST 3: SB / LB / LBU  (byte at offset 1)
        // Write 0xFF to byte address 0x301 (word=0x300, byte_offset=1)
        // LB  should sign-extend → 0xFFFFFFFF
        // LBU should zero-extend → 0x000000FF
        // ---------------------------------------------------
        $display("\n[3] SB / LB / LBU at addr=0x301 (byte offset 1)");
        write_word(32'h301, 32'h000000FF, 3'b000);    // SB
        read_word(32'h301, 3'b000);
        check("LB  0xFFFFFFFF (signed)", 32'hFFFFFFFF);
        read_word(32'h301, 3'b100);
        check("LBU 0x000000FF (unsigned)", 32'h000000FF);

        mem_read = 0;

        // ---------------------------------------------------
        // TEST 4: Verify SB only touched byte 1, not byte 0 or 2
        // Word at 0x300 should have: byte0=0x00, byte1=0xFF, byte2=0x00, byte3=0x00
        // ---------------------------------------------------
        $display("\n[4] Check SB did not corrupt adjacent bytes");
        read_word(32'h300, 3'b010);                   // LW
        check("LW word = 0x0000FF00", 32'h0000FF00);

        mem_read = 0;

        // --- SUMMARY ---
        $display("\n  %0d passed,  %0d failed", pass_count, fail_count);
        if (fail_count == 0) $display("  ALL PASSED\n");
        else                 $display("  FAILURES ABOVE ^^^\n");

        $finish;
    end

endmodule

sim_result/waves/waves_data_mem.vcd
$version Generated by VerilatedVcd $end
$timescale 1ps $end
 $scope module TOP $end
  $scope module data_mem_tb $end
   $var wire 1 - clk $end
   $var wire 1 # rst $end
   $var wire 1 $ mem_write $end
   $var wire 1 % mem_read $end
   $var wire 3 & mem_size [2:0] $end
   $var wire 32 ' addr [31:0] $end
   $var wire 32 ( data_in [31:0] $end
   $var wire 32 . data_out [31:0] $end
   $var wire 32 ) pass_count [31:0] $end
   $var wire 32 * fail_count [31:0] $end
   $scope module dut $end
    $var wire 1 - clk $end
    $var wire 1 # rst $end
    $var wire 1 $ mem_write $end
    $var wire 1 % mem_read $end
    $var wire 3 & mem_size [2:0] $end
    $var wire 32 ' addr [31:0] $end
    $var wire 32 ( data_in [31:0] $end
    $var wire 32 . data_out [31:0] $end
    $var wire 10 + word_addr [9:0] $end
    $var wire 2 , byte_offset [1:0] $end
    $var wire 32 / raw_word [31:0] $end
    $scope module unnamedblk1 $end
     $var wire 32 0 i [31:0] $end
    $upscope $end
   $upscope $end
  $upscope $end
 $upscope $end
$enddefinitions $end


#0
1#
0$
0%
b010 &
b00000000000000000000000000000000 '
b00000000000000000000000000000000 (
b00000000000000000000000000000000 )
b00000000000000000000000000000000 *
b0000000000 +
b00 ,
0-
b00000000000000000000000000000000 .
b00000000000000000000000000000000 /
b00000000000000000000000000000000 0
#5
1-
b00000000000000000000010000000000 0
#10
0-
#15
0#
1-
#20
1$
b00000000000000000000000100000000 '
b11011110101011011011111011101111 (
b0001000000 +
0-
#25
1-
b11011110101011011011111011101111 /
#26
0$
#30
1%
0-
b11011110101011011011111011101111 .
#31
0%
b00000000000000000000000000000001 )
b00000000000000000000000000000000 .
#35
1-
#40
1$
b001 &
b00000000000000000000001000000000 '
b00000000000000001010101111001101 (
b0010000000 +
0-
b00000000000000000000000000000000 /
#45
1-
b00000000000000001010101111001101 /
#46
0$
#50
1%
0-
b11111111111111111010101111001101 .
#51
b00000000000000000000000000000010 )
#55
1-
#60
b101 &
0-
b00000000000000001010101111001101 .
#61
0%
b00000000000000000000000000000011 )
b00000000000000000000000000000000 .
#65
1-
#70
1$
b000 &
b00000000000000000000001100000001 '
b00000000000000000000000011111111 (
b0011000000 +
b01 ,
0-
b00000000000000000000000000000000 /
#75
1-
b00000000000000001111111100000000 /
#76
0$
#80
1%
0-
b11111111111111111111111111111111 .
#81
b00000000000000000000000000000100 )
#85
1-
#90
b100 &
0-
b00000000000000000000000011111111 .
#91
0%
b00000000000000000000000000000101 )
b00000000000000000000000000000000 .
#95
1-
#100
1%
b010 &
b00000000000000000000001100000000 '
b00 ,
0-
b00000000000000001111111100000000 .
#101
0%
b00000000000000000000000000000110 )
b00000000000000000000000000000000 .
